paddleocr2onnx/__init__.py
paddleocr2onnx/common/__init__.py
paddleocr2onnx/common/utils.py
paddleocr2onnx/inference/__init__.py
paddleocr2onnx/inference/config.py
paddleocr2onnx/inference/hub.py
paddleocr2onnx/inference/onnx_inference.py
paddleocr2onnx/inference/process.py
paddleocr2onnx/inference/utils.py
paddleocr2onnx-0.1.2.dist-info/LICENSE
paddleocr2onnx-0.1.2.dist-info/METADATA
paddleocr2onnx-0.1.2.dist-info/WHEEL
paddleocr2onnx-0.1.2.dist-info/entry_points.txt
paddleocr2onnx-0.1.2.dist-info/top_level.txt
paddleocr2onnx-0.1.2.dist-info/RECORD
