Metadata-Version: 2.1
Name: paddleocr2onnx
Version: 0.1.2
Summary: Fast & Lightweight OCR for vehicle license plates.
Home-page: https://github.com/lidilek/paddleocr2onnx
Author: francis
Author-email: lidilek624@ofacer.com
License: MIT
Project-URL: Documentation, https://ankandrew.github.io/fast-plate-ocr
Classifier: Typing :: Typed
Classifier: Intended Audience :: Developers
Classifier: Intended Audience :: Education
Classifier: Intended Audience :: Science/Research
Classifier: Operating System :: OS Independent
Classifier: Topic :: Software Development
Classifier: Topic :: Scientific/Engineering
Classifier: Topic :: Software Development :: Libraries
Classifier: Topic :: Software Development :: Build Tools
Classifier: Topic :: Scientific/Engineering :: Artificial Intelligence
Classifier: Topic :: Software Development :: Libraries :: Python Modules
Requires-Python: >=3.10
License-File: LICENSE
Requires-Dist: numpy>=1.20
Requires-Dist: opencv-python
Requires-Dist: pyyaml>=5.1
Requires-Dist: tqdm
Requires-Dist: rich
Requires-Dist: onnxruntime>=1.19.2
